reportexport
