Metadata-Version: 1.1
Name: reportexport
Version: 0.0.2
Summary: A Flask microservice that produces reports out of a database in xml and pdf format.
Home-page: https://github.com/mdalp/reportexport
Author: Marcello Dalponte
Author-email: marcello.dalponte@gmail.com
License: BSD
Download-URL: https://github.com/mdalp/reportexport/tarball/0.0.2
Platform: UNKNOWN
Classifier: Development Status :: 3 - Alpha
Classifier: Intended Audience :: Developers
Classifier: Programming Language :: Python :: 3
